PiError.py
pierror-0.0.1a0.dist-info/METADATA
pierror-0.0.1a0.dist-info/WHEEL
pierror-0.0.1a0.dist-info/licenses/LICENSE
pierror-0.0.1a0.dist-info/RECORD
