Metadata-Version: 2.4
Name: PiError
Version: 0.0.1a0
Summary: An attempt at simplifying Python error propagation.
Project-URL: Homepage, https://github.com/sneekyfoxx/PiError
Project-URL: Issues, https://github.com/sneekyfoxx/PiError/issues
Author-email: Rayshawn Levy <sneekyfoxx09@gmail.com>
Maintainer-email: Rayshawn Levy <sneekyfoxx09@gmail.com>
License-File: LICENSE
Keywords: Error,PiError,error,error handling,pi-error,pi_error,pierror
Classifier: Development Status :: 3 - Alpha
Classifier: Intended Audience :: Developers
Classifier: Programming Language :: Python :: 3.12
Classifier: Programming Language :: Python :: 3.13
Requires-Python: >=3.13
